LICENSE
setup.py
dura/__init__.py
dura/utils.py
dura.egg-info/PKG-INFO
dura.egg-info/SOURCES.txt
dura.egg-info/dependency_links.txt
dura.egg-info/top_level.txt