Metadata-Version: 2.1
Name: dura
Version: 0.0.1
Summary: Useful function of drug discovery.
Author: auroraywood
License: UNKNOWN
Platform: UNKNOWN
License-File: LICENSE
